[{"Tour Code":"PDBRSW","Themes":["Sky Activities"],"Tour Destination":["Roman","Sal","Roma"],"Price":"$$$"},{"Tour Code":"PMBSUA","Themes":["World Heritage Site","National Park"],"Tour Destination":["Blue Mountains","Mountains","Sydney"],"Price":"$$$"},{"Tour Code":"P2G5VZ","Themes":["National Park","World Heritage Site"],"Tour Destination":["Blue Mountains","The Grand Canyon","Grand Canyon National Park","Harbour Bridge","Mountains","Sydney","Australia","Blue Mountains National Park"],"Price":"$$$"},{"Tour Code":"P293F9","Themes":["Museum","World Heritage Site"],"Tour Destination":["Botanical Gardens","Gardens","Harbour Bridge","Sydney Opera House","Baran","Sydney","Botanical Garden (Orto Botanico), Padua"],"Price":"$$"},{"Tour Code":"PNTAEX","Themes":[],"Tour Destination":["Hobart","Sydney"],"Price":"$$"},{"Tour Code":"PH86FT","Themes":[],"Tour Destination":["Sydney Tower","Sydney"],"Price":"$$"},{"Tour Code":"PPXD6R","Themes":[],"Tour Destination":["Sydney"],"Price":"$$"},{"Tour Code":"PGDTZA","Themes":[],"Tour Destination":["Sydney","Australia","Sal"],"Price":"$$"},{"Tour Code":"PMQKTP","Themes":["Water Sports"],"Tour Destination":["Sydney","Tours"],"Price":"$$"},{"Tour Code":"PDNU06","Themes":["Water Sports"],"Tour Destination":["Darling","Darling Harbour","Harbour Bridge","Sydney Opera House","Victoria","Sydney","Central"],"Price":"$$"},{"Tour Code":"PHWUNJ","Themes":["Museum","World Heritage Site"],"Tour Destination":["Museums","Museu de Marinha (Maritime Museum)","National Maritime Museum","Sydney Opera House","The Rocks","Sydney","Australia"],"Price":"$$"},{"Tour Code":"P2OHD2","Themes":["National Park"],"Tour Destination":["Sydney","Wildlife"],"Price":"$$"},{"Tour Code":"PTERWC","Themes":[],"Tour Destination":["Shiraz","Sydney","Australia","Centre"],"Price":"$$"},{"Tour Code":"PFENXW","Themes":[],"Tour Destination":["Sydney","Australia","Centre"],"Price":"$$$"},{"Tour Code":"PYXV9N","Themes":[],"Tour Destination":["Darling","Darling Harbour","Harbour Bridge","Sydney Opera House","Baran","Sydney"],"Price":"$$"},{"Tour Code":"PS1TB1","Themes":[],"Tour Destination":["Darling","Darling Harbour","Sydney"],"Price":"$$"},{"Tour Code":"PXJQ1G","Themes":["World Heritage Site"],"Tour Destination":["Harbour Bridge","Sydney Opera House","Disa","Sydney"],"Price":"$"},{"Tour Code":"P6QBCS","Themes":["Museum"],"Tour Destination":["Thailand","Australian War Memorial","Bell Tower (Campanile di San Marco)","Museo de la Nacion (National Museum)","Big Ben and the Houses of Parliament","Canberra","Australia","France","Indonesia","Malaysia","Centre","South"],"Price":"$$$"},{"Tour Code":"P4NPSG","Themes":[],"Tour Destination":["Suita"],"Price":"$$$"},{"Tour Code":"PTEDU4","Themes":[],"Tour Destination":["Sydney","Asia","South","East"],"Price":"$$"},{"Tour Code":"PCEP09","Themes":["Sky Activities"],"Tour Destination":[],"Price":"$$$"},{"Tour Code":"PJL1LF","Themes":[],"Tour Destination":[],"Price":"$$$"},{"Tour Code":"PE3C68","Themes":["Food Tour","Sky Activities"],"Tour Destination":["Wine Country"],"Price":"$$$"},{"Tour Code":"PMA1XL","Themes":[],"Tour Destination":[],"Price":"$$"},{"Tour Code":"P9ZYOL","Themes":[],"Tour Destination":["Gardens"],"Price":"$$"},{"Tour Code":"PJCC8X","Themes":[],"Tour Destination":["Hobart","Sydney","Tasmania"],"Price":"$$$"},{"Tour Code":"PXM68F","Themes":["World Heritage Site","National Park"],"Tour Destination":["Sydney Airport","Blue Mountains","Mountains","Sydney","Western"],"Price":"$"},{"Tour Code":"PZJPMN","Themes":[],"Tour Destination":["Sydney","Australia","Sal"],"Price":"$$"},{"Tour Code":"PL9RK3","Themes":["National Park","Water Sports"],"Tour Destination":["Chase National Park","Chas","Sydney","Australia","Ku-ring-gai Chase National Park"],"Price":"$"},{"Tour Code":"P3GK4A","Themes":[],"Tour Destination":["Newcastle","Sydney","Australia"],"Price":"$$$"},{"Tour Code":"PF4BTL","Themes":["Museum","World Heritage Site","National Park"],"Tour Destination":["Blue Mountains","Sydney Opera House","Mountains","Sydney"],"Price":"$$"},{"Tour Code":"PXXRWF","Themes":[],"Tour Destination":["Sydney"],"Price":"$$$"},{"Tour Code":"PWSRW8","Themes":[],"Tour Destination":["Kangar","Sydney","South"],"Price":"$$$"},{"Tour Code":"PLUVJL","Themes":[],"Tour Destination":["Kendall","South Coast","Europe","South","Tours"],"Price":"$"},{"Tour Code":"PR7Q68","Themes":[],"Tour Destination":[],"Price":"$$$"},{"Tour Code":"P7PTKU","Themes":[],"Tour Destination":["Sale","Sydney","Sal"],"Price":"$"},{"Tour Code":"PGC7WC","Themes":["World Heritage Site","National Park"],"Tour Destination":["Sydney Airport","Blue Mountains","Mountains","Sydney","Western"],"Price":"$"},{"Tour Code":"PDRRE0","Themes":[],"Tour Destination":[],"Price":"$$$"},{"Tour Code":"P240DE","Themes":["Water Sports"],"Tour Destination":["Sydney"],"Price":""},{"Tour Code":"PCQYSN","Themes":[],"Tour Destination":["Sydney","East"],"Price":"$$"},{"Tour Code":"P5GM6O","Themes":[],"Tour Destination":["Melbourne","Sydney","Side","Sal"],"Price":"$$"},{"Tour Code":"PUDNHY","Themes":["World Heritage Site"],"Tour Destination":["Gardens","Sydney Opera House","Royal Botanic Garden","Royal Botanic Gardens","Elizabeth","Sydney"],"Price":"$$"},{"Tour Code":"PMETTK","Themes":[],"Tour Destination":["Sydney","Australia","New Zealand","Centre","Burgundy"],"Price":"$$"},{"Tour Code":"PI1CLZ","Themes":[],"Tour Destination":["Montepulciano","Chia","Sydney","Italy","Centre"],"Price":"$$"},{"Tour Code":"PY1QF0","Themes":[],"Tour Destination":["Darling","Darling Harbour","Harbour Bridge","Sydney Opera House","Baran","Sydney"],"Price":"$$"},{"Tour Code":"PEHFMT","Themes":["Museum"],"Tour Destination":["Darling","Darling Harbour","Harbour Bridge","Sydney Opera House","Baran","Sydney","Europe"],"Price":"$$"},{"Tour Code":"P0ZJ0K","Themes":["World Heritage Site"],"Tour Destination":["Harbour Bridge","Sydney Opera House","Disa","Sydney"],"Price":"$"},{"Tour Code":"PE8DGE","Themes":[],"Tour Destination":["Suita"],"Price":"$$$"},{"Tour Code":"PW4YDP","Themes":[],"Tour Destination":["Suita"],"Price":"$$$"},{"Tour Code":"PNPXU9","Themes":["Water Sports"],"Tour Destination":["Canberra"],"Price":"$$"},{"Tour Code":"PTUDSF","Themes":["National Park"],"Tour Destination":["Dhar","Sydney"],"Price":"$$$"},{"Tour Code":"P9HB23","Themes":[],"Tour Destination":[],"Price":"$$$"},{"Tour Code":"PZSF0S","Themes":[],"Tour Destination":["Centre"],"Price":"$$$"},{"Tour Code":"P1TBR6","Themes":[],"Tour Destination":[],"Price":"$$$"},{"Tour Code":"PVEDI1","Themes":["National Park","Water Sports","World Heritage Site"],"Tour Destination":["Wilderness","Bath","Bush","Hobart","Tasmania","Tasmanian Wilderness","South"],"Price":"$$$"},{"Tour Code":"P4ATED","Themes":[],"Tour Destination":["Sydney"],"Price":"$$"},{"Tour Code":"P0OMAD","Themes":[],"Tour Destination":["Capri","Leon","Sydney"],"Price":"$$"},{"Tour Code":"PVHQJY","Themes":["Water Sports"],"Tour Destination":["Beaches","Harbour Bridge","Sydney","Australia","North","East"],"Price":"$$$"},{"Tour Code":"PKF6OJ","Themes":["National Park","Water Sports"],"Tour Destination":["Chase National Park","Chas","Sydney","Australia","Ku-ring-gai Chase National Park"],"Price":"$"},{"Tour Code":"P01QTK","Themes":["National Park","World Heritage Site"],"Tour Destination":["Blue Mountains","Mountains"],"Price":"$$$"},{"Tour Code":"PLW81V","Themes":[],"Tour Destination":["Darling","Darling Harbour","Harbour Bridge","Metro","Sydney"],"Price":"$$$"},{"Tour Code":"P0C0U1","Themes":["Water Sports"],"Tour Destination":["Beaches","Harbour Bridge","Sydney","Palm Beach","North","East"],"Price":"$$$"},{"Tour Code":"PQO4FR","Themes":["Museum"],"Tour Destination":["The Rocks","Tours"],"Price":"$"},{"Tour Code":"PQLZRH","Themes":[],"Tour Destination":["Beaches","East Coast","Sydney","Australia","North","East","Pai","Tours"],"Price":"$"},{"Tour Code":"PDH60X","Themes":[],"Tour Destination":[],"Price":"$$"},{"Tour Code":"PYPFYN","Themes":["National Park","World Heritage Site"],"Tour Destination":["Blue Mountains","Metro","Mountains","Sydney","Australia","Blue Mountains National Park"],"Price":"$$$"},{"Tour Code":"PC2GVV","Themes":[],"Tour Destination":["Harbour Bridge","Sydney Opera House","Islands","Sydney"],"Price":"$"},{"Tour Code":"PZ01U9","Themes":["Water Sports"],"Tour Destination":["Brooklyn","Scarborough","Sydney","Australia"],"Price":"$$$"},{"Tour Code":"PD6XET","Themes":[],"Tour Destination":["Sydney Tower","Sydney"],"Price":"$$"},{"Tour Code":"PYIUM9","Themes":["World Heritage Site","National Park"],"Tour Destination":["Blue Mountains","Featherdale Wildlife Park","Mountains","Sydney","Australia","Centre","Wildlife"],"Price":"$$$"},{"Tour Code":"P75JNG","Themes":[],"Tour Destination":["Canberra","Australia","Centre"],"Price":"$$$"},{"Tour Code":"P44CD3","Themes":["Water Sports"],"Tour Destination":["Sydney","Tours"],"Price":"$$"},{"Tour Code":"PHCZMA","Themes":["Museum"],"Tour Destination":["The Rocks"],"Price":"$"},{"Tour Code":"PMNMG1","Themes":["Museum"],"Tour Destination":["Madame Tussauds","Luxu","Sydney"],"Price":"$$$"},{"Tour Code":"PAGZLE","Themes":[],"Tour Destination":["Australia"],"Price":"$"},{"Tour Code":"PTBWPT","Themes":[],"Tour Destination":["Sydney"],"Price":"$$"},{"Tour Code":"PYP9WY","Themes":[],"Tour Destination":["Sydney"],"Price":"$$"},{"Tour Code":"P4FHTW","Themes":["World Heritage Site"],"Tour Destination":["Barossa Valley","Adelaide","Adelaide Hills","Shiraz","Sydney","Tyre","Centre"],"Price":"$$"},{"Tour Code":"PMK9RK","Themes":[],"Tour Destination":["Capri","Leon","Sydney"],"Price":"$$"},{"Tour Code":"PJWUN3","Themes":["World Heritage Site"],"Tour Destination":["Barossa Valley","Adelaide","Adelaide Hills","Shiraz","Sydney","Tyre","Australia","Centre"],"Price":"$$"},{"Tour Code":"P8FLKB","Themes":["National Park","Water Sports"],"Tour Destination":["Garigal National Park","Sydney","Tours"],"Price":"$$"},{"Tour Code":"PYXU4D","Themes":[],"Tour Destination":["Shiraz","Sydney","Centre","Alsace","Sal"],"Price":"$$$"},{"Tour Code":"PQMLJK","Themes":[],"Tour Destination":["Darling","Darling Harbour","Harbour Bridge","Sydney Opera House","Sydney","North","Central"],"Price":"$$"},{"Tour Code":"PLVF14","Themes":[],"Tour Destination":["Darling","Darling Harbour","Sydney","Australia"],"Price":"$$$"},{"Tour Code":"PV1BQT","Themes":["National Park","Water Sports","World Heritage Site"],"Tour Destination":["Sydney Opera House","Islands","Luxu","North Shore","Sydney","Australia","North"],"Price":"$$$"},{"Tour Code":"PL8DXK","Themes":[],"Tour Destination":["Darling","Darling Harbour","Harbour Bridge","Sydney Opera House","Baran","Sydney"],"Price":"$$"},{"Tour Code":"P7SN3T","Themes":["Museum","World Heritage Site"],"Tour Destination":["Museums","Museu de Marinha (Maritime Museum)","National Maritime Museum","Sydney Opera House","The Rocks","Sydney","Australia"],"Price":"$$"},{"Tour Code":"PC2NXX","Themes":[],"Tour Destination":["Disa","Sydney","Side"],"Price":"$"},{"Tour Code":"PU9XR1","Themes":[],"Tour Destination":["Assis","Suita"],"Price":"$$$"},{"Tour Code":"P6LHHY","Themes":[],"Tour Destination":["Sydney","Australia","Centre"],"Price":"$$"},{"Tour Code":"PHAL0D","Themes":[],"Tour Destination":["Central Park","Central","Clare"],"Price":"$$"},{"Tour Code":"PAXKMO","Themes":[],"Tour Destination":["Sydney","Centre"],"Price":"$$$"},{"Tour Code":"PRQNJB","Themes":["National Park","Water Sports"],"Tour Destination":["Murramarang National Park","Canberra","Kangar"],"Price":"$$$"},{"Tour Code":"PN1CEC","Themes":[],"Tour Destination":["Bordeaux","Loire Valley","Suita","Sydney","France","Centre","Burgundy","Alsace"],"Price":"$$"},{"Tour Code":"PCVL6W","Themes":[],"Tour Destination":["Gardens"],"Price":"$"},{"Tour Code":"PM53ZQ","Themes":[],"Tour Destination":["Darling","Darling Harbour","Hobart","Sydney"],"Price":"$$$"},{"Tour Code":"PWPMKJ","Themes":["Sky Activities"],"Tour Destination":["Sal","Wildlife"],"Price":"$$$"},{"Tour Code":"PR0DY3","Themes":["Food Tour"],"Tour Destination":["Wine Country","Newcastle","Swansea"],"Price":"$$$"},{"Tour Code":"PDRRUA","Themes":[],"Tour Destination":[],"Price":"$$$"},{"Tour Code":"PHZL41","Themes":["World Heritage Site"],"Tour Destination":["Harbour Bridge","Sydney Opera House","Sydney"],"Price":"$$"},{"Tour Code":"P8ZUTO","Themes":[],"Tour Destination":["Darling","Darling Harbour","Harbour Bridge","Sydney Opera House","Disa","Sydney"],"Price":"$$"},{"Tour Code":"PSKTPP","Themes":[],"Tour Destination":["Suita"],"Price":"$$$"},{"Tour Code":"PEVAPV","Themes":[],"Tour Destination":[],"Price":"$$"},{"Tour Code":"PUFEFQ","Themes":[],"Tour Destination":[],"Price":"$$$"},{"Tour Code":"PREUKC","Themes":["Sky Activities"],"Tour Destination":["Australia"],"Price":"$$$"},{"Tour Code":"PWRS3G","Themes":["Sky Activities"],"Tour Destination":["Wildlife"],"Price":"$$$"},{"Tour Code":"PP87R7","Themes":["Food Tour"],"Tour Destination":["Wine Country","Gardens"],"Price":"$$$"},{"Tour Code":"PKXBQS","Themes":["Food Tour","Sky Activities"],"Tour Destination":["Wine Country","Gardens"],"Price":"$$"},{"Tour Code":"P9GIVJ","Themes":["Water Sports"],"Tour Destination":["Port Arthur","Tasmania","South","East"],"Price":"$$$"},{"Tour Code":"PWMHRM","Themes":[],"Tour Destination":["Thailand","Kangar","Sumatra","Sydney","Asia","Tasmania","Western"],"Price":"$$"},{"Tour Code":"PNHUIB","Themes":["World Heritage Site"],"Tour Destination":["Harbour Bridge","Sydney Opera House","Sydney"],"Price":"$"},{"Tour Code":"P4RQ13","Themes":["National Park","Water Sports"],"Tour Destination":["Chas","Sydney","Australia","Goa"],"Price":"$$"},{"Tour Code":"PWBFWG","Themes":["Sky Activities"],"Tour Destination":["Camden","Sydney"],"Price":"$$$"},{"Tour Code":"PVMNMU","Themes":["National Park","Outdoor Activities","Water Sports"],"Tour Destination":["Port Arthur","East Coast","Hobart","Sydney","Australia","Tasmania","East","Freycinet National Park"],"Price":"$$$"},{"Tour Code":"PIIHKY","Themes":[],"Tour Destination":["Sydney"],"Price":"$$"},{"Tour Code":"PJR1ZN","Themes":["World Heritage Site"],"Tour Destination":["Harbour Bridge","Sydney Opera House","Sydney"],"Price":""},{"Tour Code":"P8TEKM","Themes":[],"Tour Destination":["Sydney"],"Price":"$$"},{"Tour Code":"PF6TTE","Themes":[],"Tour Destination":["Newcastle","Sydney"],"Price":"$$$"},{"Tour Code":"PXESDP","Themes":[],"Tour Destination":["Hobart","Sydney","Tasmania"],"Price":"$$"},{"Tour Code":"PSTRHA","Themes":[],"Tour Destination":["Sydney"],"Price":"$$$"},{"Tour Code":"PXWSJU","Themes":["Museum","National Park","World Heritage Site"],"Tour Destination":["Harbour Bridge","Sydney Opera House","The Rocks","Galle","Sydney"],"Price":"$$$"},{"Tour Code":"P0DT01","Themes":[],"Tour Destination":["Kendall","South Coast","Europe","South"],"Price":"$$"},{"Tour Code":"PGTOZ3","Themes":[],"Tour Destination":["Thailand","Kangar","Sumatra","Sydney","Asia","Tasmania","Western"],"Price":""},{"Tour Code":"PPXPYO","Themes":[],"Tour Destination":["Harbour Bridge","Sydney Opera House","Islands","Sydney"],"Price":""},{"Tour Code":"PGZ8WD","Themes":[],"Tour Destination":["Thailand","Kangar","Sumatra","Sydney","Asia","Tasmania","Western"],"Price":"$$"},{"Tour Code":"PQ7XHD","Themes":[],"Tour Destination":["Darling","Darling Harbour","Sydney","Australia"],"Price":"$$"},{"Tour Code":"P40F4A","Themes":["Water Sports"],"Tour Destination":["Sydney"],"Price":""},{"Tour Code":"PQLDWT","Themes":[],"Tour Destination":["Sydney"],"Price":"$$"},{"Tour Code":"PARKDM","Themes":[],"Tour Destination":["Sydney","Australia"],"Price":"$$"},{"Tour Code":"P5JHKA","Themes":["National Park"],"Tour Destination":["Sydney","Wildlife"],"Price":"$$"},{"Tour Code":"PDU6PO","Themes":[],"Tour Destination":["Sydney","Australia","Italy","Spain","Centre"],"Price":"$$"},{"Tour Code":"P0LPN2","Themes":[],"Tour Destination":["Sydney","Spain","Centre"],"Price":"$$"},{"Tour Code":"PSWAQG","Themes":["Museum","National Park","Water Sports"],"Tour Destination":["Darling","Darling Harbour","Harbour Bridge","Sydney Opera House","Baran","Sydney","North"],"Price":"$$$"},{"Tour Code":"PJZWWS","Themes":[],"Tour Destination":["Darling","Darling Harbour","Harbour Bridge","Sydney Opera House","Baran","Sydney","Australia","South"],"Price":"$$"},{"Tour Code":"P0WF9Q","Themes":["World Heritage Site"],"Tour Destination":["Darling","Darling Harbour","Harbour Bridge","Sydney Opera House","Disa","Sydney"],"Price":"$"},{"Tour Code":"PHAPGE","Themes":[],"Tour Destination":["Suita"],"Price":"$$$"},{"Tour Code":"PQYC1X","Themes":[],"Tour Destination":["Suita"],"Price":"$$$"},{"Tour Code":"PBFFZP","Themes":["Water Sports"],"Tour Destination":["Canberra"],"Price":"$$"},{"Tour Code":"PXPRTA","Themes":[],"Tour Destination":["Bari"],"Price":"$$$"},{"Tour Code":"PF1USL","Themes":["Outdoor Activities","Sky Activities"],"Tour Destination":["Centre"],"Price":"$$$"},{"Tour Code":"PUV0XH","Themes":[],"Tour Destination":[],"Price":"$$$"},{"Tour Code":"PYEZ00","Themes":[],"Tour Destination":["Gardens"],"Price":"$$"},{"Tour Code":"PLL8XH","Themes":[],"Tour Destination":["Port Arthur","Hobart","Sydney","Australia","Tasmania"],"Price":"$$$"},{"Tour Code":"PKUVO4","Themes":[],"Tour Destination":["Australia"],"Price":"$$"},{"Tour Code":"P1T4JY","Themes":[],"Tour Destination":["Sydney Tower","Sydney"],"Price":"$$"},{"Tour Code":"PVE9XG","Themes":[],"Tour Destination":["Darling","Darling Harbour","Sydney","Australia"],"Price":"$$"},{"Tour Code":"PTHQUU","Themes":["National Park","Water Sports"],"Tour Destination":["Chase National Park","Chas","Sydney","Australia","Ku-ring-gai Chase National Park"],"Price":"$"},{"Tour Code":"PT3WMD","Themes":[],"Tour Destination":["Hobart","Sydney","Wellington","Tasmania","South"],"Price":"$$"}]